mymcplus/__init__.py
mymcplus/__main__.py
mymcplus/mymc.py
mymcplus/ps2icon.py
mymcplus/ps2iconsys.py
mymcplus/ps2mc.py
mymcplus/ps2mc_dir.py
mymcplus/ps2mc_ecc.py
mymcplus/round.py
mymcplus/sjistab.py
mymcplus/utils.py
mymcplus/verbuild.py
mymcplus/gui/__init__.py
mymcplus/gui/dirlist_control.py
mymcplus/gui/gui.py
mymcplus/gui/icon_renderer.py
mymcplus/gui/icon_window.py
mymcplus/gui/linalg.py
mymcplus/gui/resources.py
mymcplus/gui/utils.py
mymcplus/save/__init__.py
mymcplus/save/format_codebreaker.py
mymcplus/save/format_ems.py
mymcplus/save/format_max_drive.py
mymcplus/save/format_psv.py
mymcplus/save/format_sharkport.py
mymcplus/save/lzari.py
mymcplus/save/ps2save.py
mymcplus/save/utils.py
mymcplus-3.0.5.dist-info/COPYING
mymcplus-3.0.5.dist-info/METADATA
mymcplus-3.0.5.dist-info/WHEEL
mymcplus-3.0.5.dist-info/entry_points.txt
mymcplus-3.0.5.dist-info/top_level.txt
mymcplus-3.0.5.dist-info/RECORD
