Metadata-Version: 2.1
Name: mymcplus
Version: 3.0.5
Summary: A PlayStation 2 memory card manager
Home-page: https://git.sr.ht/~thestr4ng3r/mymcplus
Author: Florian Märkl
License: GPLv3
Keywords: playstation ps2 mymc memory card save emulator
Platform: UNKNOWN
Requires-Python: >=3.4
Provides-Extra: gui
Requires-Dist: wxPython ; extra == 'gui'
Requires-Dist: pyopengl ; extra == 'gui'
